_multipowerrsa.cpython-310-x86_64-linux-gnu.so
_twofish.cpython-310-x86_64-linux-gnu.so
pangfish/__init__.py
pangfish/benchmark.py
pangfish/c_multipowerrsa.py
pangfish/example.py
pangfish/hybrid.py
pangfish/makeCtables.py
pangfish/myref.py
pangfish/pangfish.py
pangfish-0.7.2.dist-info/LICENSE
pangfish-0.7.2.dist-info/METADATA
pangfish-0.7.2.dist-info/WHEEL
pangfish-0.7.2.dist-info/top_level.txt
pangfish-0.7.2.dist-info/RECORD
